{
    "label": null,
    "operand": "X",
    "children": [
        {
            "label": null,
            "operand": "X",
            "children": [
                {
                    "label": "nRSesUxC",
                    "operand": "None",
                    "children": []
                },
                {
                    "label": null,
                    "operand": "*",
                    "children": [
                        {
                            "label": null,
                            "operand": "->",
                            "children": [
                                {
                                    "label": null,
                                    "operand": "*",
                                    "children": [
                                        {
                                            "label": "dyCvTOaa",
                                            "operand": "None",
                                            "children": []
                                        },
                                        {
                                            "label": "OMQUMZJo",
                                            "operand": "None",
                                            "children": []
                                        }
                                    ]
                                },
                                {
                                    "label": null,
                                    "operand": "None",
                                    "children": []
                                }
                            ]
                        },
                        {
                            "label": null,
                            "operand": "X",
                            "children": [
                                {
                                    "label": null,
                                    "operand": "->",
                                    "children": [
                                        {
                                            "label": null,
                                            "operand": "None",
                                            "children": []
                                        },
                                        {
                                            "label": null,
                                            "operand": "*",
                                            "children": [
                                                {
                                                    "label": null,
                                                    "operand": "+",
                                                    "children": [
                                                        {
                                                            "label": null,
                                                            "operand": "None",
                                                            "children": []
                                                        },
                                                        {
                                                            "label": "ZyPUXfTl",
                                                            "operand": "None",
                                                            "children": []
                                                        }
                                                    ]
                                                },
                                                {
                                                    "label": "XZkRVMDa",
                                                    "operand": "None",
                                                    "children": []
                                                }
                                            ]
                                        }
                                    ]
                                },
                                {
                                    "label": null,
                                    "operand": "None",
                                    "children": []
                                }
                            ]
                        }
                    ]
                }
            ]
        },
        {
            "label": null,
            "operand": "*",
            "children": [
                {
                    "label": "cuprtWdI",
                    "operand": "None",
                    "children": []
                },
                {
                    "label": null,
                    "operand": "X",
                    "children": [
                        {
                            "label": null,
                            "operand": "None",
                            "children": []
                        },
                        {
                            "label": "NNQcbyYw",
                            "operand": "None",
                            "children": []
                        }
                    ]
                }
            ]
        }
    ]
}