{
    "label": null,
    "operand": "->",
    "children": [
        {
            "label": null,
            "operand": "None",
            "children": []
        },
        {
            "label": null,
            "operand": "->",
            "children": [
                {
                    "label": null,
                    "operand": "+",
                    "children": [
                        {
                            "label": null,
                            "operand": "*",
                            "children": [
                                {
                                    "label": null,
                                    "operand": "->",
                                    "children": [
                                        {
                                            "label": null,
                                            "operand": "None",
                                            "children": []
                                        },
                                        {
                                            "label": null,
                                            "operand": "X",
                                            "children": [
                                                {
                                                    "label": "mOtpR",
                                                    "operand": "None",
                                                    "children": []
                                                },
                                                {
                                                    "label": "MfKFi",
                                                    "operand": "None",
                                                    "children": []
                                                }
                                            ]
                                        }
                                    ]
                                },
                                {
                                    "label": null,
                                    "operand": "X",
                                    "children": [
                                        {
                                            "label": "rkZHd",
                                            "operand": "None",
                                            "children": []
                                        },
                                        {
                                            "label": "zRzaP",
                                            "operand": "None",
                                            "children": []
                                        }
                                    ]
                                }
                            ]
                        },
                        {
                            "label": "tQkwB",
                            "operand": "None",
                            "children": []
                        }
                    ]
                },
                {
                    "label": null,
                    "operand": "*",
                    "children": [
                        {
                            "label": null,
                            "operand": "->",
                            "children": [
                                {
                                    "label": null,
                                    "operand": "*",
                                    "children": [
                                        {
                                            "label": null,
                                            "operand": "None",
                                            "children": []
                                        },
                                        {
                                            "label": "fOIoQ",
                                            "operand": "None",
                                            "children": []
                                        }
                                    ]
                                },
                                {
                                    "label": null,
                                    "operand": "None",
                                    "children": []
                                }
                            ]
                        },
                        {
                            "label": "WoLEK",
                            "operand": "None",
                            "children": []
                        }
                    ]
                }
            ]
        }
    ]
}