{
    "label": null,
    "operand": "->",
    "children": [
        {
            "label": null,
            "operand": "+",
            "children": [
                {
                    "label": "lbwdaR",
                    "operand": "None",
                    "children": []
                },
                {
                    "label": "iprwNa",
                    "operand": "None",
                    "children": []
                }
            ]
        },
        {
            "label": null,
            "operand": "+",
            "children": [
                {
                    "label": null,
                    "operand": "*",
                    "children": [
                        {
                            "label": null,
                            "operand": "X",
                            "children": [
                                {
                                    "label": null,
                                    "operand": "->",
                                    "children": [
                                        {
                                            "label": null,
                                            "operand": "None",
                                            "children": []
                                        },
                                        {
                                            "label": "KKIFQJ",
                                            "operand": "None",
                                            "children": []
                                        }
                                    ]
                                },
                                {
                                    "label": "kfpeaz",
                                    "operand": "None",
                                    "children": []
                                }
                            ]
                        },
                        {
                            "label": null,
                            "operand": "X",
                            "children": [
                                {
                                    "label": "AvPMUa",
                                    "operand": "None",
                                    "children": []
                                },
                                {
                                    "label": "eurPIe",
                                    "operand": "None",
                                    "children": []
                                }
                            ]
                        }
                    ]
                },
                {
                    "label": null,
                    "operand": "+",
                    "children": [
                        {
                            "label": "WEZyZx",
                            "operand": "None",
                            "children": []
                        },
                        {
                            "label": null,
                            "operand": "None",
                            "children": []
                        }
                    ]
                }
            ]
        }
    ]
}