{
    "label": null,
    "operand": "->",
    "children": [
        {
            "label": null,
            "operand": "*",
            "children": [
                {
                    "label": null,
                    "operand": "*",
                    "children": [
                        {
                            "label": null,
                            "operand": "None",
                            "children": []
                        },
                        {
                            "label": null,
                            "operand": "X",
                            "children": [
                                {
                                    "label": null,
                                    "operand": "X",
                                    "children": [
                                        {
                                            "label": "gczmlcux",
                                            "operand": "None",
                                            "children": []
                                        },
                                        {
                                            "label": null,
                                            "operand": "None",
                                            "children": []
                                        }
                                    ]
                                },
                                {
                                    "label": null,
                                    "operand": "None",
                                    "children": []
                                }
                            ]
                        }
                    ]
                },
                {
                    "label": null,
                    "operand": "->",
                    "children": [
                        {
                            "label": null,
                            "operand": "+",
                            "children": [
                                {
                                    "label": "ZWuErNTZ",
                                    "operand": "None",
                                    "children": []
                                },
                                {
                                    "label": null,
                                    "operand": "None",
                                    "children": []
                                }
                            ]
                        },
                        {
                            "label": "WqKbPMgl",
                            "operand": "None",
                            "children": []
                        }
                    ]
                }
            ]
        },
        {
            "label": null,
            "operand": "X",
            "children": [
                {
                    "label": null,
                    "operand": "X",
                    "children": [
                        {
                            "label": null,
                            "operand": "->",
                            "children": [
                                {
                                    "label": "ZYUatmoi",
                                    "operand": "None",
                                    "children": []
                                },
                                {
                                    "label": null,
                                    "operand": "None",
                                    "children": []
                                }
                            ]
                        },
                        {
                            "label": null,
                            "operand": "*",
                            "children": [
                                {
                                    "label": "fUJwFaEp",
                                    "operand": "None",
                                    "children": []
                                },
                                {
                                    "label": "SZVeHfUj",
                                    "operand": "None",
                                    "children": []
                                }
                            ]
                        }
                    ]
                },
                {
                    "label": null,
                    "operand": "*",
                    "children": [
                        {
                            "label": "FXIalSNg",
                            "operand": "None",
                            "children": []
                        },
                        {
                            "label": null,
                            "operand": "None",
                            "children": []
                        }
                    ]
                }
            ]
        }
    ]
}