{
    "label": null,
    "operand": "+",
    "children": [
        {
            "label": null,
            "operand": "*",
            "children": [
                {
                    "label": null,
                    "operand": "->",
                    "children": [
                        {
                            "label": null,
                            "operand": "X",
                            "children": [
                                {
                                    "label": null,
                                    "operand": "None",
                                    "children": []
                                },
                                {
                                    "label": null,
                                    "operand": "+",
                                    "children": [
                                        {
                                            "label": "NQKezQU",
                                            "operand": "None",
                                            "children": []
                                        },
                                        {
                                            "label": "XQAjnvY",
                                            "operand": "None",
                                            "children": []
                                        }
                                    ]
                                }
                            ]
                        },
                        {
                            "label": null,
                            "operand": "->",
                            "children": [
                                {
                                    "label": null,
                                    "operand": "None",
                                    "children": []
                                },
                                {
                                    "label": null,
                                    "operand": "None",
                                    "children": []
                                }
                            ]
                        }
                    ]
                },
                {
                    "label": null,
                    "operand": "+",
                    "children": [
                        {
                            "label": null,
                            "operand": "*",
                            "children": [
                                {
                                    "label": "VmlSXre",
                                    "operand": "None",
                                    "children": []
                                },
                                {
                                    "label": null,
                                    "operand": "+",
                                    "children": [
                                        {
                                            "label": "qumgyKv",
                                            "operand": "None",
                                            "children": []
                                        },
                                        {
                                            "label": "YWgLCut",
                                            "operand": "None",
                                            "children": []
                                        }
                                    ]
                                }
                            ]
                        },
                        {
                            "label": "wfLpPYs",
                            "operand": "None",
                            "children": []
                        }
                    ]
                }
            ]
        },
        {
            "label": null,
            "operand": "X",
            "children": [
                {
                    "label": "qeBczQp",
                    "operand": "None",
                    "children": []
                },
                {
                    "label": null,
                    "operand": "None",
                    "children": []
                }
            ]
        }
    ]
}