{
    "label": null,
    "operand": "+",
    "children": [
        {
            "label": null,
            "operand": "+",
            "children": [
                {
                    "label": null,
                    "operand": "X",
                    "children": [
                        {
                            "label": null,
                            "operand": "->",
                            "children": [
                                {
                                    "label": null,
                                    "operand": "->",
                                    "children": [
                                        {
                                            "label": null,
                                            "operand": "X",
                                            "children": [
                                                {
                                                    "label": null,
                                                    "operand": "None",
                                                    "children": []
                                                },
                                                {
                                                    "label": "xLOKQ",
                                                    "operand": "None",
                                                    "children": []
                                                }
                                            ]
                                        },
                                        {
                                            "label": "hEohB",
                                            "operand": "None",
                                            "children": []
                                        }
                                    ]
                                },
                                {
                                    "label": null,
                                    "operand": "None",
                                    "children": []
                                }
                            ]
                        },
                        {
                            "label": "wNZDV",
                            "operand": "None",
                            "children": []
                        }
                    ]
                },
                {
                    "label": null,
                    "operand": "*",
                    "children": [
                        {
                            "label": null,
                            "operand": "+",
                            "children": [
                                {
                                    "label": "JVEBz",
                                    "operand": "None",
                                    "children": []
                                },
                                {
                                    "label": "hJINM",
                                    "operand": "None",
                                    "children": []
                                }
                            ]
                        },
                        {
                            "label": "IRwTc",
                            "operand": "None",
                            "children": []
                        }
                    ]
                }
            ]
        },
        {
            "label": null,
            "operand": "->",
            "children": [
                {
                    "label": "pFCrq",
                    "operand": "None",
                    "children": []
                },
                {
                    "label": null,
                    "operand": "None",
                    "children": []
                }
            ]
        }
    ]
}