{
    "label": null,
    "operand": "+",
    "children": [
        {
            "label": null,
            "operand": "X",
            "children": [
                {
                    "label": "zjazU",
                    "operand": "None",
                    "children": []
                },
                {
                    "label": null,
                    "operand": "X",
                    "children": [
                        {
                            "label": null,
                            "operand": "None",
                            "children": []
                        },
                        {
                            "label": "cBFrj",
                            "operand": "None",
                            "children": []
                        }
                    ]
                }
            ]
        },
        {
            "label": null,
            "operand": "X",
            "children": [
                {
                    "label": null,
                    "operand": "+",
                    "children": [
                        {
                            "label": "tyEdY",
                            "operand": "None",
                            "children": []
                        },
                        {
                            "label": null,
                            "operand": "->",
                            "children": [
                                {
                                    "label": null,
                                    "operand": "+",
                                    "children": [
                                        {
                                            "label": "PbWkO",
                                            "operand": "None",
                                            "children": []
                                        },
                                        {
                                            "label": null,
                                            "operand": "None",
                                            "children": []
                                        }
                                    ]
                                },
                                {
                                    "label": null,
                                    "operand": "X",
                                    "children": [
                                        {
                                            "label": null,
                                            "operand": "None",
                                            "children": []
                                        },
                                        {
                                            "label": "HgUBh",
                                            "operand": "None",
                                            "children": []
                                        }
                                    ]
                                }
                            ]
                        }
                    ]
                },
                {
                    "label": null,
                    "operand": "*",
                    "children": [
                        {
                            "label": null,
                            "operand": "*",
                            "children": [
                                {
                                    "label": "WoSCw",
                                    "operand": "None",
                                    "children": []
                                },
                                {
                                    "label": null,
                                    "operand": "None",
                                    "children": []
                                }
                            ]
                        },
                        {
                            "label": null,
                            "operand": "+",
                            "children": [
                                {
                                    "label": "RANuZ",
                                    "operand": "None",
                                    "children": []
                                },
                                {
                                    "label": null,
                                    "operand": "None",
                                    "children": []
                                }
                            ]
                        }
                    ]
                }
            ]
        }
    ]
}