{
    "label": null,
    "operand": "+",
    "children": [
        {
            "label": null,
            "operand": "*",
            "children": [
                {
                    "label": null,
                    "operand": "X",
                    "children": [
                        {
                            "label": null,
                            "operand": "*",
                            "children": [
                                {
                                    "label": null,
                                    "operand": "*",
                                    "children": [
                                        {
                                            "label": null,
                                            "operand": "None",
                                            "children": []
                                        },
                                        {
                                            "label": "GMLLTCAx",
                                            "operand": "None",
                                            "children": []
                                        }
                                    ]
                                },
                                {
                                    "label": "HPwYtAPa",
                                    "operand": "None",
                                    "children": []
                                }
                            ]
                        },
                        {
                            "label": "NBSmXeje",
                            "operand": "None",
                            "children": []
                        }
                    ]
                },
                {
                    "label": null,
                    "operand": "->",
                    "children": [
                        {
                            "label": "dgVvuSmh",
                            "operand": "None",
                            "children": []
                        },
                        {
                            "label": "BIgLvowe",
                            "operand": "None",
                            "children": []
                        }
                    ]
                }
            ]
        },
        {
            "label": null,
            "operand": "+",
            "children": [
                {
                    "label": null,
                    "operand": "+",
                    "children": [
                        {
                            "label": null,
                            "operand": "None",
                            "children": []
                        },
                        {
                            "label": null,
                            "operand": "None",
                            "children": []
                        }
                    ]
                },
                {
                    "label": null,
                    "operand": "X",
                    "children": [
                        {
                            "label": "vtLVbLvg",
                            "operand": "None",
                            "children": []
                        },
                        {
                            "label": "MSDqAEMx",
                            "operand": "None",
                            "children": []
                        }
                    ]
                }
            ]
        }
    ]
}