{
    "label": null,
    "operand": "+",
    "children": [
        {
            "label": null,
            "operand": "->",
            "children": [
                {
                    "label": null,
                    "operand": "*",
                    "children": [
                        {
                            "label": null,
                            "operand": "X",
                            "children": [
                                {
                                    "label": null,
                                    "operand": "None",
                                    "children": []
                                },
                                {
                                    "label": null,
                                    "operand": "None",
                                    "children": []
                                }
                            ]
                        },
                        {
                            "label": null,
                            "operand": "->",
                            "children": [
                                {
                                    "label": null,
                                    "operand": "None",
                                    "children": []
                                },
                                {
                                    "label": "uKvdNgD",
                                    "operand": "None",
                                    "children": []
                                }
                            ]
                        }
                    ]
                },
                {
                    "label": null,
                    "operand": "*",
                    "children": [
                        {
                            "label": null,
                            "operand": "->",
                            "children": [
                                {
                                    "label": null,
                                    "operand": "*",
                                    "children": [
                                        {
                                            "label": "HYzEuuc",
                                            "operand": "None",
                                            "children": []
                                        },
                                        {
                                            "label": "ljRrmOt",
                                            "operand": "None",
                                            "children": []
                                        }
                                    ]
                                },
                                {
                                    "label": "PvyHBFK",
                                    "operand": "None",
                                    "children": []
                                }
                            ]
                        },
                        {
                            "label": null,
                            "operand": "X",
                            "children": [
                                {
                                    "label": null,
                                    "operand": "X",
                                    "children": [
                                        {
                                            "label": null,
                                            "operand": "None",
                                            "children": []
                                        },
                                        {
                                            "label": "qCxgzNg",
                                            "operand": "None",
                                            "children": []
                                        }
                                    ]
                                },
                                {
                                    "label": "KieztaK",
                                    "operand": "None",
                                    "children": []
                                }
                            ]
                        }
                    ]
                }
            ]
        },
        {
            "label": null,
            "operand": "X",
            "children": [
                {
                    "label": null,
                    "operand": "None",
                    "children": []
                },
                {
                    "label": null,
                    "operand": "+",
                    "children": [
                        {
                            "label": "hXIgkOZ",
                            "operand": "None",
                            "children": []
                        },
                        {
                            "label": null,
                            "operand": "->",
                            "children": [
                                {
                                    "label": null,
                                    "operand": "None",
                                    "children": []
                                },
                                {
                                    "label": null,
                                    "operand": "None",
                                    "children": []
                                }
                            ]
                        }
                    ]
                }
            ]
        }
    ]
}