{
    "label": null,
    "operand": "X",
    "children": [
        {
            "label": null,
            "operand": "+",
            "children": [
                {
                    "label": null,
                    "operand": "->",
                    "children": [
                        {
                            "label": "vBNPfo",
                            "operand": "None",
                            "children": []
                        },
                        {
                            "label": null,
                            "operand": "*",
                            "children": [
                                {
                                    "label": null,
                                    "operand": "None",
                                    "children": []
                                },
                                {
                                    "label": "obmKzW",
                                    "operand": "None",
                                    "children": []
                                }
                            ]
                        }
                    ]
                },
                {
                    "label": null,
                    "operand": "->",
                    "children": [
                        {
                            "label": null,
                            "operand": "+",
                            "children": [
                                {
                                    "label": "JJnWNs",
                                    "operand": "None",
                                    "children": []
                                },
                                {
                                    "label": "sgsKQq",
                                    "operand": "None",
                                    "children": []
                                }
                            ]
                        },
                        {
                            "label": null,
                            "operand": "->",
                            "children": [
                                {
                                    "label": "PrIOec",
                                    "operand": "None",
                                    "children": []
                                },
                                {
                                    "label": "lKQkpO",
                                    "operand": "None",
                                    "children": []
                                }
                            ]
                        }
                    ]
                }
            ]
        },
        {
            "label": "rXbJKM",
            "operand": "None",
            "children": []
        }
    ]
}