{
    "label": null,
    "operand": "X",
    "children": [
        {
            "label": "iIPuX",
            "operand": "None",
            "children": []
        },
        {
            "label": null,
            "operand": "X",
            "children": [
                {
                    "label": "kcbbL",
                    "operand": "None",
                    "children": []
                },
                {
                    "label": null,
                    "operand": "+",
                    "children": [
                        {
                            "label": null,
                            "operand": "->",
                            "children": [
                                {
                                    "label": null,
                                    "operand": "X",
                                    "children": [
                                        {
                                            "label": null,
                                            "operand": "X",
                                            "children": [
                                                {
                                                    "label": "QPtQd",
                                                    "operand": "None",
                                                    "children": []
                                                },
                                                {
                                                    "label": null,
                                                    "operand": "None",
                                                    "children": []
                                                }
                                            ]
                                        },
                                        {
                                            "label": null,
                                            "operand": "*",
                                            "children": [
                                                {
                                                    "label": "kQEtI",
                                                    "operand": "None",
                                                    "children": []
                                                },
                                                {
                                                    "label": "EgiNW",
                                                    "operand": "None",
                                                    "children": []
                                                }
                                            ]
                                        }
                                    ]
                                },
                                {
                                    "label": "cEone",
                                    "operand": "None",
                                    "children": []
                                }
                            ]
                        },
                        {
                            "label": "APipc",
                            "operand": "None",
                            "children": []
                        }
                    ]
                }
            ]
        }
    ]
}