{
    "label": null,
    "operand": "X",
    "children": [
        {
            "label": null,
            "operand": "X",
            "children": [
                {
                    "label": null,
                    "operand": "*",
                    "children": [
                        {
                            "label": "QIgDUIW",
                            "operand": "None",
                            "children": []
                        },
                        {
                            "label": "wqEbAUv",
                            "operand": "None",
                            "children": []
                        }
                    ]
                },
                {
                    "label": "QtETAwr",
                    "operand": "None",
                    "children": []
                }
            ]
        },
        {
            "label": null,
            "operand": "X",
            "children": [
                {
                    "label": null,
                    "operand": "->",
                    "children": [
                        {
                            "label": null,
                            "operand": "+",
                            "children": [
                                {
                                    "label": "TVDhLWK",
                                    "operand": "None",
                                    "children": []
                                },
                                {
                                    "label": "DFkYOZk",
                                    "operand": "None",
                                    "children": []
                                }
                            ]
                        },
                        {
                            "label": "GufCHPS",
                            "operand": "None",
                            "children": []
                        }
                    ]
                },
                {
                    "label": "nUddymh",
                    "operand": "None",
                    "children": []
                }
            ]
        }
    ]
}